gcnu_common/__init__.py
gcnu_common/numerical_methods/__init__.py
gcnu_common/numerical_methods/utils.py
gcnu_common/resampling/__init__.py
gcnu_common/resampling/bootstrapTests.py
gcnu_common/stats/__init__.py
gcnu_common/stats/gaussianProcesses/__init__.py
gcnu_common/stats/gaussianProcesses/eval.py
gcnu_common/stats/gaussianProcesses/kernels.py
gcnu_common/stats/gaussianProcesses/learn.py
gcnu_common/stats/pointProcesses/__init__.py
gcnu_common/stats/pointProcesses/sampling.py
gcnu_common/stats/pointProcesses/tests.py
gcnu_common/utils/__init__.py
gcnu_common/utils/argparse.py
gcnu_common/utils/config_dict.py
gcnu_common/utils/multi_processing.py
gcnu_common/utils/neural_data_analysis.py
gcnu_common/utils/spectral_analysis.py
gcnu_common-0.0.15.dist-info/METADATA
gcnu_common-0.0.15.dist-info/WHEEL
gcnu_common-0.0.15.dist-info/top_level.txt
gcnu_common-0.0.15.dist-info/RECORD
